setup.py
tmpr/__init__.py
tmpr/__main__.py
tmpr/util.py
tmpr/web.py
tmpr.egg-info/PKG-INFO
tmpr.egg-info/SOURCES.txt
tmpr.egg-info/dependency_links.txt
tmpr.egg-info/entry_points.txt
tmpr.egg-info/not-zip-safe
tmpr.egg-info/requires.txt
tmpr.egg-info/top_level.txt