Metadata-Version: 1.0
Name: tmpr
Version: 0.5.0
Summary: Temporary file sharing using simple two digit codes.
Home-page: https://github.com/mattbierbaum/tmpr
Author: Matt Bierbaum
Author-email: UNKNOWN
License: MIT License
Platform: osx
Platform: posix
Platform: linux
Platform: windows
